threaded_context.py
threaded_context-1.2.2.dist-info/LICENSE
threaded_context-1.2.2.dist-info/WHEEL
threaded_context-1.2.2.dist-info/METADATA
threaded_context-1.2.2.dist-info/RECORD
