Metadata-Version: 2.1
Name: threaded-context
Version: 1.2.2
Summary: Basic context manager with inheritance management.
License: GNU General Public License v3 (GPLv3)
Author: François Schmidts
Author-email: francois@schmidts.fr
Requires-Python: >=3.7,<4.0
Classifier: License :: Other/Proprietary License
Classifier: Programming Language :: Python :: 3
Classifier: Programming Language :: Python :: 3.7
Classifier: Programming Language :: Python :: 3.8
Classifier: Programming Language :: Python :: 3.9
